{
 "prices": {
  "HMC.AX": {
   "price": 2.94,
   "currency": "AUD",
   "name": "HMC Capital Limited"
  },
  "DGT.AX": {
   "price": 2.65,
   "currency": "AUD",
   "name": "DIGICO INF STAPLED [DGT]"
  },
  "TUA.AX": {
   "price": 2.32,
   "currency": "AUD",
   "name": "Tuas Limited"
  },
  "SGO.PA": {
   "price": 76.74,
   "currency": "EUR",
   "name": "Compagnie de Saint-Gobain S.A."
  },
  "PSN.L": {
   "price": 10.895,
   "currency": "GBP",
   "name": "Persimmon Plc"
  },
  "RMV.L": {
   "price": 4.487,
   "currency": "GBP",
   "name": "Rightmove plc"
  }
 },
 "fx": {
  "AUDAUD": 1.0,
  "USDAUD": 1.4271,
  "GBPAUD": 1.92727,
  "EURAUD": 1.6367,
  "HKDAUD": 0.18205,
  "SGDAUD": 1.10738,
  "JPYAUD": 0.008797
 },
 "tiles": {
  "AU": 22489950.0,
  "US": 0.0,
  "UK": 6793600.0,
  "EU": 1534800.0,
  "ASIA_AUD": 0.0,
  "TOTAL_AUD": 38095059.06
 },
 "checked": {
  "AU": "2026-07-16T18:22:46+10:00",
  "US": "2026-07-16T18:22:46+10:00",
  "UK": "2026-07-16T18:22:46+10:00",
  "FR": "2026-07-16T18:22:46+10:00",
  "NL": "2026-07-16T18:22:46+10:00",
  "BE": "2026-07-16T18:22:46+10:00",
  "DE": "2026-07-16T18:22:46+10:00",
  "HK": "2026-07-16T21:56:18+10:00",
  "SG": "2026-07-16T21:56:18+10:00",
  "JP": "2026-07-16T18:22:46+10:00"
 },
 "history": [
  {
   "date": "2026-07-15",
   "au": 20769950.0,
   "us": 0.0,
   "uk": 6741200.0,
   "total_aud": 33722558.85,
   "usdaud": 1.4296,
   "gbpaud": 1.92141
  },
  {
   "date": "2026-07-16",
   "au": 22489950.0,
   "us": 0.0,
   "uk": 6793600.0,
   "eu": 1534800.0,
   "asia_aud": 0.0,
   "total_aud": 38095059.06,
   "fx": {
    "USDAUD": 1.4271,
    "GBPAUD": 1.92727,
    "EURAUD": 1.6367,
    "HKDAUD": 0.18205,
    "SGDAUD": 1.10738,
    "JPYAUD": 0.008797
   }
  }
 ],
 "errors": [],
 "updated_at": "2026-07-16T21:56:18+10:00"
}